LICENSE.txt
MANIFEST.in
README.rst
requirements.txt
setup.cfg
setup.py
redongo/__init__.py
redongo/__init__.pyc
redongo/cipher_utils.py
redongo/cipher_utils.pyc
redongo/client_exceptions.py
redongo/client_exceptions.pyc
redongo/general_exceptions.py
redongo/general_exceptions.pyc
redongo/queue_utils.py
redongo/queue_utils.pyc
redongo/redongo_client.py
redongo/redongo_client.pyc
redongo/redongo_server.py
redongo/redongo_server.pyc
redongo/serializer_utils.py
redongo/serializer_utils.pyc
redongo/server_exceptions.py
redongo/server_exceptions.pyc
redongo/utils.py
redongo/utils.pyc
redongo.egg-info/PKG-INFO
redongo.egg-info/SOURCES.txt
redongo.egg-info/dependency_links.txt
redongo.egg-info/pbr.json
redongo.egg-info/requires.txt
redongo.egg-info/top_level.txt
tests/__init__.py
tests/__init__.pyc
tests/client/__init__.py
tests/client/__init__.pyc
tests/client/test_client.py
tests/client/__pycache__/test_client.cpython-27-PYTEST.pyc
tests/server/__init__.py
tests/server/__init__.pyc
tests/server/test_server.py
tests/server/__pycache__/test_server.cpython-27-PYTEST.pyc