Metadata-Version: 1.1
Name: redongo
Version: 0.4.2
Summary: Gets stuff from a Redis queue and inserts it in Mongo
Home-page: https://github.com/stoneworksolutions/redongo
Author: StoneWork Solutions
Author-email: dev@stoneworksolutions.net
License: UNKNOWN
Download-URL: https://github.com/stoneworksolutions/redongo/tarball/0.4.2
Keywords: redis,mongo,bulks
Platform: UNKNOWN
